{
  "slug": "angebot-nachfassen-handwerker",
  "title": "Angebot nachfassen: So verlieren Handwerker weniger Aufträge",
  "excerpt": "Viele Angebote versanden, weil niemand nachfasst. Mit einem klaren 3-Tage-Rhythmus holst du mehr Zusagen – ohne aufdringlich zu wirken.",
  "body": "Ein Angebot zu schicken reicht oft nicht. Kunden sind beschäftigt, vergleichen oder vergessen einfach.\n\n**Was funktioniert:**\n1. Angebot mit klarem Link senden\n2. Sehen, ob es geöffnet wurde\n3. Nach 3 Tagen freundlich nachfassen\n\nDer Nachfasst-Text darf kurz sein: ob Fragen offen sind, und dass du bei Bedarf erreichbar bist.\n\nMeisterFlow erinnert dich automatisch und öffnet WhatsApp oder E-Mail mit fertigem Text – damit Aufträge nicht in der Schublade landen.",
  "published_at": "2026-07-10T10:00:00.000Z"
}
